cdm_ecommerce/bin/__init__.py
cdm_ecommerce/bin/cdm_manage.py
cdm_ecommerce/config/__init__.py
cdm_ecommerce/config/asgi.py
cdm_ecommerce/config/settings.py
cdm_ecommerce/config/urls.py
cdm_ecommerce/config/utilities.py
cdm_ecommerce/config/wsgi.py
cdm_ecommerce/meds/__init__.py
cdm_ecommerce/meds/models.py
cdm_ecommerce/meds/views.py
cdm_ecommerce/meds/migrations/0001_initial.py
cdm_ecommerce/meds/migrations/__init__.py
cdm_ecommerce_backend-0.1.0.dist-info/licenses/LICENSE
cdm_ecommerce_backend-0.1.0.dist-info/METADATA
cdm_ecommerce_backend-0.1.0.dist-info/WHEEL
cdm_ecommerce_backend-0.1.0.dist-info/entry_points.txt
cdm_ecommerce_backend-0.1.0.dist-info/top_level.txt
cdm_ecommerce_backend-0.1.0.dist-info/RECORD
