Metadata-Version: 2.4
Name: cdm-ecommerce-backend
Version: 0.1.0
Summary: CDM ecommerce backend.
Author-email: Michael <okwizifr@gmail.com>
License-Expression: Apache-2.0
Project-URL: Homepage, https://github.com/Okwizi/CDM-eCommerce-backend
Project-URL: Repository, https://github.com/Okwizi/CDM-eCommerce-backend.git
Project-URL: Issues, https://github.com/Okwizi/CDM-eCommerce-backend/issues
Keywords: django,cdm,pharmacy,ecommerce,medicine,django-rest-framework,store
Classifier: Development Status :: 3 - Alpha
Classifier: Intended Audience :: Developers
Classifier: Natural Language :: English
Classifier: Topic :: Software Development :: Build Tools
Classifier: Programming Language :: Python :: 3
Classifier: Programming Language :: Python :: 3.12
Classifier: Framework :: Django
Classifier: Operating System :: OS Independent
Classifier: Programming Language :: C
Classifier: Environment :: Web Environment
Classifier: Framework :: Django :: 5.2
Classifier: Typing :: Typed
Classifier: Topic :: Software Development :: Libraries :: Python Modules
Requires-Python: >=3.12
License-File: LICENSE
Requires-Dist: django==5.2.3
Requires-Dist: djangorestframework==3.16.0
Requires-Dist: django-extensions==4.1
Requires-Dist: django-cors-headers==4.7.0
Requires-Dist: psycopg==3.2.9
Requires-Dist: uv==0.7.3
Requires-Dist: ipython==9.2.0
Requires-Dist: git-changelog
Provides-Extra: dev
Requires-Dist: uv; extra == "dev"
Provides-Extra: test
Requires-Dist: pytest==8.3.5; extra == "test"
Requires-Dist: pytest-cov==6.1.1; extra == "test"
Requires-Dist: pytest-testmon==2.1.3; extra == "test"
Requires-Dist: pytest-xdist==3.6.1; extra == "test"
Requires-Dist: pytest-django==4.11.1; extra == "test"
Requires-Dist: pytest-faulthandler==2.0.1; extra == "test"
Requires-Dist: model-bakery==1.20.4; extra == "test"
Requires-Dist: pdbpp==0.11.6; extra == "test"
Requires-Dist: pep257==0.7.0; extra == "test"
Provides-Extra: ci
Requires-Dist: ruff==0.11.9; extra == "ci"
Requires-Dist: pyright==1.1.400; extra == "ci"
Requires-Dist: pre-commit==4.2.0; extra == "ci"
Requires-Dist: conventional-pre-commit==4.2.0; extra == "ci"
Requires-Dist: tox==4.26.0; extra == "ci"
Requires-Dist: tox-uv==1.25.0; extra == "ci"
Requires-Dist: setuptools>=75.1.0; extra == "ci"
Requires-Dist: setuptools-scm==8.3.1; extra == "ci"
Dynamic: license-file
